{
  "sections": {
    "main": {
      "type": "main-page",
      "settings": {
        "padding_top": 28,
        "padding_bottom": 28
      }
    },
    "rich_text_eLbhh3": {
      "type": "rich-text",
      "blocks": {
        "heading_NxjUqX": {
          "type": "heading",
          "settings": {
            "heading": "Talk about your brand",
            "heading_size": "h1"
          }
        },
        "text_Y8hjtp": {
          "type": "text",
          "settings": {
            "text": "<p>Share information about your brand with your customers. Describe a product, make announcements, or welcome customers to your store.<\/p>"
          }
        },
        "button_PQwwrg": {
          "type": "button",
          "settings": {
            "button_label": "Button label",
            "button_link": "",
            "button_style_secondary": false,
            "button_label_2": "",
            "button_link_2": "",
            "button_style_secondary_2": false
          }
        }
      },
      "block_order": [
        "heading_NxjUqX",
        "text_Y8hjtp",
        "button_PQwwrg"
      ],
      "settings": {
        "desktop_content_position": "center",
        "content_alignment": "left",
        "color_scheme": "",
        "full_width": true,
        "padding_top": 40,
        "padding_bottom": 52
      }
    },
    "multicolumn_a96xPT": {
      "type": "multicolumn",
      "blocks": {
        "column_TUaUt6": {
          "type": "column",
          "settings": {
            "title": "Column",
            "text": "<p>Pair text with an image to focus on your chosen product, collection, or blog post. Add details on availability, style, or even provide a review.<\/p>",
            "link_label": "",
            "link": ""
          }
        },
        "column_HzgDXb": {
          "type": "column",
          "settings": {
            "title": "Column",
            "text": "<p>Pair text with an image to focus on your chosen product, collection, or blog post. Add details on availability, style, or even provide a review.<\/p>",
            "link_label": "",
            "link": ""
          }
        },
        "column_a3ckDm": {
          "type": "column",
          "settings": {
            "image": "shopify:\/\/shop_images\/image_094438aa-4837-4e05-978d-d3c6ef581263.jpg",
            "title": "",
            "text": "",
            "link_label": "",
            "link": ""
          }
        }
      },
      "block_order": [
        "column_TUaUt6",
        "column_HzgDXb",
        "column_a3ckDm"
      ],
      "settings": {
        "title": "Multicolumn",
        "heading_size": "h1",
        "image_width": "full",
        "image_ratio": "adapt",
        "columns_desktop": 4,
        "column_alignment": "left",
        "background_style": "primary",
        "button_label": "Button label",
        "button_link": "",
        "color_scheme": "",
        "columns_mobile": "1",
        "swipe_on_mobile": false,
        "padding_top": 36,
        "padding_bottom": 36
      }
    }
  },
  "order": [
    "main",
    "rich_text_eLbhh3",
    "multicolumn_a96xPT"
  ]
}
